replaykit/__init__.py
replaykit/main.py
replaykit-0.2.0.dist-info/METADATA
replaykit-0.2.0.dist-info/WHEEL
replaykit-0.2.0.dist-info/entry_points.txt
replaykit-0.2.0.dist-info/licenses/LICENSE
replaykit-0.2.0.dist-info/RECORD
