Metadata-Version: 2.4
Name: replaykit
Version: 0.2.0
Summary: Record and replay mouse, keyboard, and scroll actions for automation
Project-URL: Homepage, https://github.com/zkhan93/replaykit
Project-URL: Repository, https://github.com/zkhan93/replaykit
Project-URL: Issues, https://github.com/zkhan93/replaykit/issues
Author-email: Zeeshan Khan <zkhan1093@gmail.com>
License: MIT
License-File: LICENSE
Keywords: automation,keyboard,macro,mouse,playback,recorder
Classifier: Development Status :: 4 - Beta
Classifier: Intended Audience :: Developers
Classifier: License :: OSI Approved :: MIT License
Classifier: Operating System :: OS Independent
Classifier: Programming Language :: Python :: 3
Classifier: Programming Language :: Python :: 3.9
Classifier: Programming Language :: Python :: 3.10
Classifier: Programming Language :: Python :: 3.11
Classifier: Programming Language :: Python :: 3.12
Classifier: Topic :: Software Development :: Testing
Classifier: Topic :: System :: Monitoring
Requires-Python: >=3.9
Requires-Dist: pyautogui>=0.9.54
Requires-Dist: pynput>=1.8.1
Requires-Dist: pyyaml>=6.0.2
Requires-Dist: rich>=14.1.0
Requires-Dist: typer>=0.19.2
Provides-Extra: macos
Requires-Dist: pyobjc-core>=10.0; extra == 'macos'
Requires-Dist: pyobjc-framework-quartz>=10.0; extra == 'macos'
